{
    "dashboard": {
        "id": "Redmine-Backlog",
        "value": {
            "dashboard": {
                "description": "Redmine Backlog panel by Bitergia",
                "hits": 0,
                "kibanaSavedObjectMeta": {
                    "searchSourceJSON": "{\"query\":{\"language\":\"lucene\",\"query\":{\"query_string\":{\"analyze_wildcard\":true,\"default_field\":\"*\",\"query\":\"*\",\"time_zone\":\"Europe/Madrid\"}}},\"highlightAll\":true,\"version\":true,\"filter\":[{\"meta\":{\"negate\":true,\"disabled\":false,\"alias\":\"Bots\",\"type\":\"phrase\",\"key\":\"author_bot\",\"params\":{\"query\":true},\"indexRefName\":\"kibanaSavedObjectMeta.searchSourceJSON.filter[0].meta.index\"},\"query\":{\"match\":{\"author_bot\":{\"query\":true,\"type\":\"phrase\"}}},\"$state\":{\"store\":\"appState\"}}]}"
                },
                "optionsJSON": "{\"darkTheme\":false,\"useMargins\":true}",
                "panelsJSON": "[{\"version\":\"7.9.1\",\"gridData\":{\"x\":0,\"y\":0,\"w\":28,\"h\":6,\"i\":\"1\"},\"panelIndex\":\"1\",\"embeddableConfig\":{\"title\":\"Open Issues Statistics\"},\"title\":\"Open Issues Statistics\",\"panelRefName\":\"panel_0\"},{\"version\":\"7.9.1\",\"gridData\":{\"x\":32,\"y\":25,\"w\":16,\"h\":20,\"i\":\"2\"},\"panelIndex\":\"2\",\"embeddableConfig\":{\"title\":\"Projects\"},\"title\":\"Projects\",\"panelRefName\":\"panel_1\"},{\"version\":\"7.9.1\",\"gridData\":{\"x\":28,\"y\":0,\"w\":20,\"h\":6,\"i\":\"3\"},\"panelIndex\":\"3\",\"embeddableConfig\":{\"title\":\"Backlog\"},\"title\":\"Backlog\",\"panelRefName\":\"panel_2\"},{\"version\":\"7.9.1\",\"gridData\":{\"x\":0,\"y\":6,\"w\":28,\"h\":19,\"i\":\"4\"},\"panelIndex\":\"4\",\"embeddableConfig\":{\"title\":\"Backlog\",\"vis\":{\"params\":{\"sort\":{\"columnIndex\":null,\"direction\":null}}}},\"title\":\"Backlog\",\"panelRefName\":\"panel_3\"},{\"version\":\"7.9.1\",\"gridData\":{\"x\":28,\"y\":6,\"w\":20,\"h\":6,\"i\":\"5\"},\"panelIndex\":\"5\",\"embeddableConfig\":{\"title\":\"Backlog: Issues (Accumulated Time)\"},\"title\":\"Backlog: Issues (Accumulated Time)\",\"panelRefName\":\"panel_4\"},{\"version\":\"7.9.1\",\"gridData\":{\"x\":0,\"y\":25,\"w\":16,\"h\":20,\"i\":\"6\"},\"panelIndex\":\"6\",\"embeddableConfig\":{\"title\":\"Backlog Submitters\"},\"title\":\"Backlog Submitters\",\"panelRefName\":\"panel_5\"},{\"version\":\"7.9.1\",\"gridData\":{\"x\":28,\"y\":12,\"w\":20,\"h\":13,\"i\":\"9\"},\"panelIndex\":\"9\",\"embeddableConfig\":{\"title\":\"Organizations\"},\"title\":\"Organizations\",\"panelRefName\":\"panel_6\"},{\"version\":\"7.9.1\",\"gridData\":{\"x\":16,\"y\":25,\"w\":16,\"h\":20,\"i\":\"10\"},\"panelIndex\":\"10\",\"embeddableConfig\":{\"title\":\"Organizations\"},\"title\":\"Organizations\",\"panelRefName\":\"panel_7\"}]",
                "timeRestore": false,
                "title": "Redmine Backlog",
                "version": 1
            },
            "references": [
                {
                    "id": "redmine",
                    "name": "kibanaSavedObjectMeta.searchSourceJSON.filter[0].meta.index",
                    "type": "index-pattern"
                },
                {
                    "id": "redmine_openissues_statistics",
                    "name": "panel_0",
                    "type": "visualization"
                },
                {
                    "id": "redmine_openissues_projects",
                    "name": "panel_1",
                    "type": "visualization"
                },
                {
                    "id": "redmine_openissues_backlog",
                    "name": "panel_2",
                    "type": "visualization"
                },
                {
                    "id": "redmine_backlog",
                    "name": "panel_3",
                    "type": "visualization"
                },
                {
                    "id": "redmine_openissues_backlog_accumulated_time",
                    "name": "panel_4",
                    "type": "visualization"
                },
                {
                    "id": "redmine_openissues_submitters",
                    "name": "panel_5",
                    "type": "visualization"
                },
                {
                    "id": "56e93a80-7ea1-11e8-a4e7-6b1c6a13c58d",
                    "name": "panel_6",
                    "type": "visualization"
                },
                {
                    "id": "6849d130-7ea2-11e8-a4e7-6b1c6a13c58d",
                    "name": "panel_7",
                    "type": "visualization"
                }
            ],
            "release_date": "2020-12-01T16:24:58.454561"
        }
    },
    "searches": [
        {
            "id": "Open-Redmine-Issues-Search:_-status_name:resolved_rejected_closed_wontfix_duplicate",
            "value": {
                "references": [
                    {
                        "id": "redmine",
                        "name": "kibanaSavedObjectMeta.searchSourceJSON.index",
                        "type": "index-pattern"
                    }
                ],
                "search": {
                    "columns": [
                        "_source"
                    ],
                    "description": "",
                    "hits": 0,
                    "kibanaSavedObjectMeta": {
                        "searchSourceJSON": "{\"query\":{\"query\":{\"query_string\":{\"query\":\"-status_name:(\\\"Resolved\\\" \\\"Rejected\\\" \\\"Closed\\\" \\\"Won\\\\'t Fix\\\" \\\"Duplicate\\\")\",\"analyze_wildcard\":true}},\"language\":\"lucene\"},\"highlight\":{\"pre_tags\":[\"@kibana-highlighted-field@\"],\"post_tags\":[\"@/kibana-highlighted-field@\"],\"fields\":{\"*\":{}},\"require_field_match\":false,\"fragment_size\":2147483647},\"filter\":[],\"indexRefName\":\"kibanaSavedObjectMeta.searchSourceJSON.index\"}"
                    },
                    "sort": [
                        [
                            "grimoire_creation_date",
                            "desc"
                        ]
                    ],
                    "title": "Open Redmine Issues Search:_-status_name:resolved_rejected_closed_wontfix_duplicate",
                    "version": 1
                }
            }
        }
    ],
    "visualizations": [
        {
            "id": "redmine_openissues_statistics",
            "value": {
                "references": [
                    {
                        "id": "Open-Redmine-Issues-Search:_-status_name:resolved_rejected_closed_wontfix_duplicate",
                        "name": "search_0",
                        "type": "search"
                    }
                ],
                "visualization": {
                    "description": "",
                    "kibanaSavedObjectMeta": {
                        "searchSourceJSON": "{\"filter\":[]}"
                    },
                    "savedSearchRefName": "search_0",
                    "title": "redmine_openissues_statistics",
                    "uiStateJSON": "{}",
                    "version": 1,
                    "visState": "{\"title\":\"redmine_openissues_statistics\",\"type\":\"metric\",\"params\":{\"fontSize\":\"12\",\"metric\":{\"percentageMode\":false,\"useRanges\":false,\"colorSchema\":\"Green to Red\",\"metricColorMode\":\"None\",\"colorsRange\":[{\"from\":0,\"to\":10000}],\"labels\":{\"show\":true},\"invertColors\":false,\"style\":{\"bgFill\":\"#000\",\"bgColor\":false,\"labelColor\":false,\"subText\":\"\",\"fontSize\":\"12\"}}},\"aggs\":[{\"id\":\"1\",\"type\":\"count\",\"schema\":\"metric\",\"params\":{\"customLabel\":\"Open Issues\"}},{\"id\":\"2\",\"type\":\"sum\",\"schema\":\"metric\",\"params\":{\"field\":\"timeopen_days\",\"customLabel\":\"Accumulated Open Days\"}},{\"id\":\"3\",\"type\":\"avg\",\"schema\":\"metric\",\"params\":{\"field\":\"timeopen_days\",\"customLabel\":\"Average Time Open Days per Issue\"}}],\"listeners\":{}}"
                }
            }
        },
        {
            "id": "redmine_openissues_projects",
            "value": {
                "references": [
                    {
                        "id": "Open-Redmine-Issues-Search:_-status_name:resolved_rejected_closed_wontfix_duplicate",
                        "name": "search_0",
                        "type": "search"
                    }
                ],
                "visualization": {
                    "description": "",
                    "kibanaSavedObjectMeta": {
                        "searchSourceJSON": "{\"filter\":[],\"query\":{\"query\":\"\",\"language\":\"lucene\"}}"
                    },
                    "savedSearchRefName": "search_0",
                    "title": "redmine_openissues_projects",
                    "uiStateJSON": "{\"vis\":{\"params\":{\"sort\":{\"columnIndex\":null,\"direction\":null}}}}",
                    "version": 1,
                    "visState": "{\"title\":\"redmine_openissues_projects\",\"type\":\"table\",\"params\":{\"perPage\":5,\"showPartialRows\":false,\"sort\":{\"columnIndex\":null,\"direction\":null},\"showTotal\":false,\"totalFunc\":\"sum\",\"showMetricsAtAllLevels\":false},\"aggs\":[{\"id\":\"1\",\"enabled\":true,\"type\":\"count\",\"schema\":\"metric\",\"params\":{\"customLabel\":\"Issues\"}},{\"id\":\"5\",\"enabled\":true,\"type\":\"cardinality\",\"schema\":\"metric\",\"params\":{\"field\":\"author_uuid\",\"customLabel\":\"Submitters\"}},{\"id\":\"4\",\"enabled\":true,\"type\":\"cardinality\",\"schema\":\"metric\",\"params\":{\"field\":\"assigned_to_uuid\",\"customLabel\":\"Assignees\"}},{\"id\":\"2\",\"enabled\":true,\"type\":\"avg\",\"schema\":\"metric\",\"params\":{\"field\":\"timeopen_days\",\"customLabel\":\"Avg. Time Open (Days)\"}},{\"id\":\"3\",\"enabled\":true,\"type\":\"terms\",\"schema\":\"bucket\",\"params\":{\"field\":\"project_name\",\"size\":1000,\"order\":\"desc\",\"orderBy\":\"1\",\"customLabel\":\"Project\"}}]}"
                }
            }
        },
        {
            "id": "redmine_openissues_backlog",
            "value": {
                "references": [
                    {
                        "id": "Open-Redmine-Issues-Search:_-status_name:resolved_rejected_closed_wontfix_duplicate",
                        "name": "search_0",
                        "type": "search"
                    }
                ],
                "visualization": {
                    "description": "",
                    "kibanaSavedObjectMeta": {
                        "searchSourceJSON": "{\"filter\":[],\"query\":{\"query\":\"\",\"language\":\"lucene\"}}"
                    },
                    "savedSearchRefName": "search_0",
                    "title": "redmine_openissues_backlog",
                    "uiStateJSON": "{}",
                    "version": 1,
                    "visState": "{\"title\":\"redmine_openissues_backlog\",\"type\":\"histogram\",\"params\":{\"shareYAxis\":true,\"addTooltip\":true,\"addLegend\":true,\"scale\":\"linear\",\"mode\":\"stacked\",\"times\":[],\"addTimeMarker\":false,\"defaultYExtents\":false,\"setYExtents\":false,\"yAxis\":{},\"type\":\"histogram\",\"grid\":{\"categoryLines\":false,\"style\":{\"color\":\"#eee\"}},\"categoryAxes\":[{\"id\":\"CategoryAxis-1\",\"type\":\"category\",\"position\":\"bottom\",\"show\":true,\"style\":{},\"scale\":{\"type\":\"linear\"},\"labels\":{\"show\":true,\"truncate\":100},\"title\":{}}],\"valueAxes\":[{\"id\":\"ValueAxis-1\",\"name\":\"LeftAxis-1\",\"type\":\"value\",\"position\":\"left\",\"show\":true,\"style\":{},\"scale\":{\"type\":\"linear\",\"mode\":\"normal\",\"setYExtents\":false,\"defaultYExtents\":false},\"labels\":{\"show\":true,\"rotate\":0,\"filter\":false,\"truncate\":100},\"title\":{\"text\":\"Issues\"}}],\"seriesParams\":[{\"show\":\"true\",\"type\":\"histogram\",\"mode\":\"stacked\",\"data\":{\"label\":\"Issues\",\"id\":\"1\"},\"valueAxis\":\"ValueAxis-1\"}],\"legendPosition\":\"right\"},\"aggs\":[{\"id\":\"1\",\"enabled\":true,\"type\":\"count\",\"schema\":\"metric\",\"params\":{\"customLabel\":\"Issues\"}},{\"id\":\"2\",\"enabled\":true,\"type\":\"date_histogram\",\"schema\":\"segment\",\"params\":{\"field\":\"grimoire_creation_date\",\"interval\":\"auto\",\"min_doc_count\":1,\"extended_bounds\":{},\"customLabel\":\"Time\"}}]}"
                }
            }
        },
        {
            "id": "redmine_backlog",
            "value": {
                "references": [
                    {
                        "id": "Open-Redmine-Issues-Search:_-status_name:resolved_rejected_closed_wontfix_duplicate",
                        "name": "search_0",
                        "type": "search"
                    }
                ],
                "visualization": {
                    "description": "",
                    "kibanaSavedObjectMeta": {
                        "searchSourceJSON": "{\"filter\":[]}"
                    },
                    "savedSearchRefName": "search_0",
                    "title": "redmine_backlog",
                    "uiStateJSON": "{}",
                    "version": 1,
                    "visState": "{\"title\":\"redmine_backlog\",\"type\":\"table\",\"params\":{\"perPage\":10,\"showPartialRows\":false,\"showMetricsAtAllLevels\":false},\"aggs\":[{\"id\":\"1\",\"type\":\"avg\",\"schema\":\"metric\",\"params\":{\"field\":\"timeopen_days\",\"customLabel\":\"Days Open\"}},{\"id\":\"2\",\"type\":\"terms\",\"schema\":\"bucket\",\"params\":{\"field\":\"subject\",\"size\":100,\"order\":\"desc\",\"orderBy\":\"1\",\"customLabel\":\"Title\"}},{\"id\":\"3\",\"type\":\"terms\",\"schema\":\"bucket\",\"params\":{\"field\":\"url\",\"size\":1000,\"order\":\"desc\",\"orderBy\":\"1\",\"customLabel\":\"+ Info\"}},{\"id\":\"4\",\"type\":\"terms\",\"schema\":\"bucket\",\"params\":{\"field\":\"project_name\",\"size\":1000,\"order\":\"desc\",\"orderBy\":\"1\",\"customLabel\":\"Project\"}},{\"id\":\"5\",\"type\":\"terms\",\"schema\":\"bucket\",\"params\":{\"field\":\"author_name\",\"size\":1000,\"order\":\"desc\",\"orderBy\":\"1\",\"customLabel\":\"Submitter\"}}],\"listeners\":{}}"
                }
            }
        },
        {
            "id": "redmine_openissues_backlog_accumulated_time",
            "value": {
                "references": [
                    {
                        "id": "Open-Redmine-Issues-Search:_-status_name:resolved_rejected_closed_wontfix_duplicate",
                        "name": "search_0",
                        "type": "search"
                    }
                ],
                "visualization": {
                    "description": "",
                    "kibanaSavedObjectMeta": {
                        "searchSourceJSON": "{\"filter\":[]}"
                    },
                    "savedSearchRefName": "search_0",
                    "title": "redmine_openissues_backlog_accumulated_time",
                    "uiStateJSON": "{}",
                    "version": 1,
                    "visState": "{\"title\":\"New Visualization\",\"type\":\"histogram\",\"params\":{\"shareYAxis\":true,\"addTooltip\":true,\"addLegend\":true,\"scale\":\"linear\",\"mode\":\"stacked\",\"times\":[],\"addTimeMarker\":false,\"defaultYExtents\":false,\"setYExtents\":false,\"yAxis\":{}},\"aggs\":[{\"id\":\"1\",\"type\":\"sum\",\"schema\":\"metric\",\"params\":{\"field\":\"timeopen_days\",\"customLabel\":\"Acc. Days Open\"}},{\"id\":\"2\",\"type\":\"date_histogram\",\"schema\":\"segment\",\"params\":{\"field\":\"grimoire_creation_date\",\"interval\":\"auto\",\"min_doc_count\":1,\"extended_bounds\":{},\"customLabel\":\"Time\"}}],\"listeners\":{}}"
                }
            }
        },
        {
            "id": "redmine_openissues_submitters",
            "value": {
                "references": [
                    {
                        "id": "Open-Redmine-Issues-Search:_-status_name:resolved_rejected_closed_wontfix_duplicate",
                        "name": "search_0",
                        "type": "search"
                    }
                ],
                "visualization": {
                    "description": "",
                    "kibanaSavedObjectMeta": {
                        "searchSourceJSON": "{\"filter\":[],\"query\":{\"query\":\"\",\"language\":\"lucene\"}}"
                    },
                    "savedSearchRefName": "search_0",
                    "title": "redmine_openissues_submitters",
                    "uiStateJSON": "{\"vis\":{\"params\":{\"sort\":{\"columnIndex\":null,\"direction\":null}}}}",
                    "version": 1,
                    "visState": "{\"title\":\"redmine_openissues_submitters\",\"type\":\"table\",\"params\":{\"perPage\":10,\"showPartialRows\":false,\"sort\":{\"columnIndex\":null,\"direction\":null},\"showTotal\":false,\"totalFunc\":\"sum\",\"showMetricsAtAllLevels\":false},\"aggs\":[{\"id\":\"1\",\"enabled\":true,\"type\":\"count\",\"schema\":\"metric\",\"params\":{\"customLabel\":\"Issues\"}},{\"id\":\"2\",\"enabled\":true,\"type\":\"avg\",\"schema\":\"metric\",\"params\":{\"field\":\"timeopen_days\",\"customLabel\":\"Avg. Open Days\"}},{\"id\":\"3\",\"enabled\":true,\"type\":\"cardinality\",\"schema\":\"metric\",\"params\":{\"field\":\"project_name\",\"customLabel\":\"Projects\"}},{\"id\":\"4\",\"enabled\":true,\"type\":\"terms\",\"schema\":\"bucket\",\"params\":{\"field\":\"author_name\",\"size\":1000,\"order\":\"desc\",\"orderBy\":\"1\",\"customLabel\":\"Submitter\"}}]}"
                }
            }
        },
        {
            "id": "56e93a80-7ea1-11e8-a4e7-6b1c6a13c58d",
            "value": {
                "references": [
                    {
                        "id": "Open-Redmine-Issues-Search:_-status_name:resolved_rejected_closed_wontfix_duplicate",
                        "name": "search_0",
                        "type": "search"
                    }
                ],
                "visualization": {
                    "description": "",
                    "kibanaSavedObjectMeta": {
                        "searchSourceJSON": "{\"filter\":[],\"query\":{\"query\":\"\",\"language\":\"lucene\"}}"
                    },
                    "savedSearchRefName": "search_0",
                    "title": "redmine_openissues_assignee_orgs",
                    "uiStateJSON": "{}",
                    "version": 1,
                    "visState": "{\"title\":\"redmine_openissues_assignee_orgs\",\"type\":\"pie\",\"params\":{\"type\":\"pie\",\"addTooltip\":true,\"addLegend\":true,\"legendPosition\":\"right\",\"isDonut\":true,\"labels\":{\"show\":false,\"values\":true,\"last_level\":true,\"truncate\":100}},\"aggs\":[{\"id\":\"1\",\"enabled\":true,\"type\":\"count\",\"schema\":\"metric\",\"params\":{}},{\"id\":\"2\",\"enabled\":true,\"type\":\"terms\",\"schema\":\"segment\",\"params\":{\"field\":\"assigned_to_org_name\",\"size\":50000,\"order\":\"desc\",\"orderBy\":\"1\",\"customLabel\":\"Organization\"}}]}"
                }
            }
        },
        {
            "id": "6849d130-7ea2-11e8-a4e7-6b1c6a13c58d",
            "value": {
                "references": [
                    {
                        "id": "Open-Redmine-Issues-Search:_-status_name:resolved_rejected_closed_wontfix_duplicate",
                        "name": "search_0",
                        "type": "search"
                    }
                ],
                "visualization": {
                    "description": "",
                    "kibanaSavedObjectMeta": {
                        "searchSourceJSON": "{\"filter\":[],\"query\":{\"query\":\"\",\"language\":\"lucene\"}}"
                    },
                    "savedSearchRefName": "search_0",
                    "title": "redmine_openissues_per_organization",
                    "uiStateJSON": "{\"vis\":{\"params\":{\"sort\":{\"columnIndex\":null,\"direction\":null}}}}",
                    "version": 1,
                    "visState": "{\"title\":\"redmine_openissues_per_organization\",\"type\":\"table\",\"params\":{\"perPage\":10,\"showPartialRows\":false,\"sort\":{\"columnIndex\":null,\"direction\":null},\"showTotal\":false,\"totalFunc\":\"sum\",\"showMetricsAtAllLevels\":false},\"aggs\":[{\"id\":\"1\",\"enabled\":true,\"type\":\"count\",\"schema\":\"metric\",\"params\":{\"customLabel\":\"Open Issues\"}},{\"id\":\"2\",\"enabled\":true,\"type\":\"cardinality\",\"schema\":\"metric\",\"params\":{\"field\":\"author_uuid\",\"customLabel\":\"Submitters\"}},{\"id\":\"3\",\"enabled\":true,\"type\":\"cardinality\",\"schema\":\"metric\",\"params\":{\"field\":\"assigned_to_uuid\",\"customLabel\":\"Assignees\"}},{\"id\":\"4\",\"enabled\":true,\"type\":\"avg\",\"schema\":\"metric\",\"params\":{\"field\":\"timeopen_days\",\"customLabel\":\"Avg. Open Days\"}},{\"id\":\"5\",\"enabled\":true,\"type\":\"terms\",\"schema\":\"bucket\",\"params\":{\"field\":\"assigned_to_org_name\",\"size\":50000,\"order\":\"desc\",\"orderBy\":\"1\",\"customLabel\":\"Organization\"}}]}"
                }
            }
        }
    ]
}